<?xml version="1.0" encoding="UTF-8"?>
<calibration status="1">
    <point x="0" y="0">
        <sample left_x="0" left_y="0" left_validity="-1" right_x="0" right_y="0" right_validity="-1"/>
        <sample left_x="0" left_y="0" left_validity="-1" right_x="0" right_y="0" right_validity="-1"/>
        <sample left_x="0" left_y="0" left_validity="-1" right_x="0" right_y="0" right_validity="-1"/>
        <sample left_x="0" left_y="0" left_validity="-1" right_x="0" right_y="0" right_validity="-1"/>
        <sample left_x="0" left_y="0" left_validity="-1" right_x="0" right_y="0" right_validity="-1"/>
    </point>
    <point x="0.5" y="0.5">
        <sample left_x="0.515481" left_y="0.549715" left_validity="1" right_x="0.515669" right_y="0.510587" right_validity="1"/>
        <sample left_x="0.472168" left_y="0.514544" left_validity="1" right_x="0" right_y="0" right_validity="-1"/>
        <sample left_x="0.441941" left_y="0.590819" left_validity="1" right_x="0.498062" right_y="0.496491" right_validity="1"/>
    </point>
    <point x="0.5" y="0.9">
        <sample left_x="0.491927" left_y="0.896424" left_validity="1" right_x="0.500796" right_y="0.839967" right_validity="1"/>
        <sample left_x="0.551347" left_y="0.94068" left_validity="1" right_x="0.512245" right_y="0.847289" right_validity="1"/>
        <sample left_x="0.525953" left_y="0.882784" left_validity="1" right_x="0.513866" right_y="0.914497" right_validity="1"/>
    </point>
    <point x="0.5" y="0.1">
        <sample left_x="0.483592" left_y="0.115892" left_validity="1" right_x="0.495256" right_y="0.207143" right_validity="1"/>
        <sample left_x="0.447609" left_y="0.126377" left_validity="1" right_x="0.471488" right_y="0.177204" right_validity="1"/>
        <sample left_x="0" left_y="0" left_validity="-1" right_x="0.488515" right_y="0.129417" right_validity="1"/>
    </point>
    <point x="0.9" y="0.5">
        <sample left_x="0.849368" left_y="0.485096" left_validity="1" right_x="0" right_y="0" right_validity="-1"/>
        <sample left_x="0.888185" left_y="0.529513" left_validity="1" right_x="0" right_y="0" right_validity="-1"/>
        <sample left_x="0.889823" left_y="0.521754" left_validity="1" right_x="0.911646" right_y="0.55703" right_validity="1"/>
    </point>
    <point x="0.9" y="0.9">
        <sample left_x="0.902983" left_y="0.818567" left_validity="1" right_x="0.89259" right_y="0.890136" right_validity="1"/>
        <sample left_x="0.88744" left_y="0.896108" left_validity="1" right_x="0.897245" right_y="0.828288" right_validity="1"/>
        <sample left_x="0" left_y="0" left_validity="-1" right_x="0.919605" right_y="0.912827" right_validity="1"/>
    </point>
    <point x="0.9" y="0.1">
        <sample left_x="0.847582" left_y="-0.172638" left_validity="1" right_x="0" right_y="0" right_validity="-1"/>
        <sample left_x="0.898822" left_y="0.0644149" left_validity="1" right_x="0.895315" right_y="0.131368" right_validity="1"/>
        <sample left_x="0.90535" left_y="-0.11403" left_validity="1" right_x="0" right_y="0" right_validity="-1"/>
    </point>
    <point x="0.1" y="0.5">
        <sample left_x="0.150899" left_y="0.599404" left_validity="1" right_x="0.100811" right_y="0.499837" right_validity="1"/>
        <sample left_x="0.0943838" left_y="0.528396" left_validity="1" right_x="0.097692" right_y="0.512718" right_validity="1"/>
        <sample left_x="0.0667752" left_y="0.544401" left_validity="1" right_x="0.126352" right_y="0.532858" right_validity="1"/>
    </point>
    <point x="0.1" y="0.9">
        <sample left_x="0.0890417" left_y="0.84518" left_validity="1" right_x="0.128844" right_y="0.837485" right_validity="1"/>
        <sample left_x="0" left_y="0" left_validity="-1" right_x="0.1171" right_y="0.8331" right_validity="1"/>
        <sample left_x="0.0971384" left_y="0.887619" left_validity="1" right_x="0.142858" right_y="0.995242" right_validity="1"/>
    </point>
    <point x="0.1" y="0.1">
        <sample left_x="0.219296" left_y="0.414051" left_validity="1" right_x="0.0660727" right_y="0.0391678" right_validity="1"/>
        <sample left_x="0.123016" left_y="0.227113" left_validity="1" right_x="0.052033" right_y="0.0402841" right_validity="1"/>
        <sample left_x="0" left_y="0" left_validity="-1" right_x="0.0730456" right_y="0.0979306" right_validity="1"/>
    </point>
</calibration>
