<?xml version="1.0" encoding="UTF-8"?>
<calibration status="1">
    <point x="0" y="0">
        <sample left_x="0" left_y="0" left_validity="-1" right_x="0" right_y="0" right_validity="-1"/>
        <sample left_x="0" left_y="0" left_validity="-1" right_x="0" right_y="0" right_validity="-1"/>
        <sample left_x="0" left_y="0" left_validity="-1" right_x="0" right_y="0" right_validity="-1"/>
        <sample left_x="0" left_y="0" left_validity="-1" right_x="0" right_y="0" right_validity="-1"/>
        <sample left_x="0" left_y="0" left_validity="-1" right_x="0" right_y="0" right_validity="-1"/>
        <sample left_x="0" left_y="0" left_validity="-1" right_x="0" right_y="0" right_validity="-1"/>
    </point>
    <point x="0.5" y="0.5">
        <sample left_x="0.496378" left_y="0.51136" left_validity="1" right_x="0.497289" right_y="0.466346" right_validity="1"/>
        <sample left_x="0.51095" left_y="0.46442" left_validity="1" right_x="0.502385" right_y="0.526131" right_validity="1"/>
        <sample left_x="0.497415" left_y="0.497035" left_validity="1" right_x="0.504617" right_y="0.502504" right_validity="1"/>
    </point>
    <point x="0.5" y="0.9">
        <sample left_x="0.539682" left_y="0.945836" left_validity="1" right_x="0.493692" right_y="0.920861" right_validity="1"/>
        <sample left_x="0.495133" left_y="0.910799" left_validity="1" right_x="0.48485" right_y="0.913271" right_validity="1"/>
        <sample left_x="0.499055" left_y="0.894724" left_validity="1" right_x="0.46111" right_y="0.927218" right_validity="1"/>
    </point>
    <point x="0.5" y="0.1">
        <sample left_x="0.507227" left_y="0.122298" left_validity="1" right_x="0.504132" right_y="0.101785" right_validity="1"/>
        <sample left_x="0.513195" left_y="0.0800583" left_validity="1" right_x="0.503982" right_y="0.081475" right_validity="1"/>
        <sample left_x="0.519358" left_y="0.0781886" left_validity="1" right_x="0.509869" right_y="0.0854063" right_validity="1"/>
    </point>
    <point x="0.9" y="0.5">
        <sample left_x="0.87972" left_y="0.478671" left_validity="1" right_x="0.902361" right_y="0.522198" right_validity="1"/>
        <sample left_x="0.89147" left_y="0.481175" left_validity="1" right_x="0.883452" right_y="0.52913" right_validity="1"/>
        <sample left_x="0.89831" left_y="0.47211" left_validity="1" right_x="0" right_y="0" right_validity="-1"/>
    </point>
    <point x="0.9" y="0.9">
        <sample left_x="0.899879" left_y="0.866166" left_validity="1" right_x="0" right_y="0" right_validity="-1"/>
        <sample left_x="0.909585" left_y="0.900676" left_validity="1" right_x="0.867802" right_y="0.955819" right_validity="1"/>
        <sample left_x="0.891627" left_y="0.902902" left_validity="1" right_x="0.896501" right_y="0.931154" right_validity="1"/>
    </point>
    <point x="0.9" y="0.1">
        <sample left_x="0.879252" left_y="0.119523" left_validity="1" right_x="0.919695" right_y="0.0911511" right_validity="1"/>
        <sample left_x="0.891163" left_y="0.103813" left_validity="1" right_x="0" right_y="0" right_validity="-1"/>
        <sample left_x="0.875669" left_y="0.0675259" left_validity="1" right_x="0.918639" right_y="0.118085" right_validity="1"/>
    </point>
    <point x="0.1" y="0.5">
        <sample left_x="0.0943235" left_y="0.536424" left_validity="1" right_x="0.108556" right_y="0.482699" right_validity="1"/>
        <sample left_x="0.114577" left_y="0.52751" left_validity="1" right_x="0.105946" right_y="0.453514" right_validity="1"/>
        <sample left_x="0.0921322" left_y="0.509287" left_validity="1" right_x="0.108272" right_y="0.485963" right_validity="1"/>
    </point>
    <point x="0.1" y="0.9">
        <sample left_x="0.122794" left_y="0.938865" left_validity="1" right_x="0.0801661" right_y="0.894126" right_validity="1"/>
        <sample left_x="0" left_y="0" left_validity="-1" right_x="0.0891102" right_y="0.87175" right_validity="1"/>
        <sample left_x="0.104654" left_y="0.950486" left_validity="1" right_x="0.0973615" right_y="0.878547" right_validity="1"/>
    </point>
    <point x="0.1" y="0.1">
        <sample left_x="0.102766" left_y="0.0830161" left_validity="1" right_x="0.126008" right_y="0.0831489" right_validity="1"/>
        <sample left_x="0.0735523" left_y="0.065638" left_validity="1" right_x="0.118163" right_y="0.0937422" right_validity="1"/>
        <sample left_x="0" left_y="0" left_validity="-1" right_x="0.130216" right_y="0.0887625" right_validity="1"/>
    </point>
</calibration>
